MANIFEST.in
README.md
VERSION
setup.py
gdctools/GDCcore.py
gdctools/GDCtool.py
gdctools/__init__.py
gdctools/default.cfg
gdctools/gdc_dice.py
gdctools/gdc_list.py
gdctools/gdc_loadfile.py
gdctools/gdc_mirror.py
gdctools/gdc_report.py
gdctools/tool_template.py
gdctools.egg-info/PKG-INFO
gdctools.egg-info/SOURCES.txt
gdctools.egg-info/dependency_links.txt
gdctools.egg-info/entry_points.txt
gdctools.egg-info/requires.txt
gdctools.egg-info/top_level.txt
gdctools/config/cptac3.cfg
gdctools/config/google.cfg
gdctools/config/tcga.cfg
gdctools/lib/GDCSampleReport.R
gdctools/lib/__init__.py
gdctools/lib/annotations_table.tsv
gdctools/lib/api.py
gdctools/lib/clinxml.py
gdctools/lib/common.py
gdctools/lib/heatmap.py
gdctools/lib/meta.py
gdctools/lib/convert/__init__.py
gdctools/lib/convert/copy.py
gdctools/lib/convert/maf.py
gdctools/lib/convert/py_clinical.py
gdctools/lib/convert/seg.py
gdctools/lib/convert/tsv2idtsv.py
gdctools/lib/convert/tsv2magetab.py
gdctools/reference/centerCode.txt
gdctools/reference/diseaseStudy.txt
gdctools/reference/platformCode.txt
gdctools/reference/sampleType.txt