Metadata-Version: 1.0
Name: gdctools
Version: 0.2.12
Summary: GDCtools: Python and UNIX CLI utils to simplify interaction with the NIH/NCI Genomics Data Commons.
Home-page: https://github.com/broadinstitute/gdctools
Author: Michael S. Noble, Timothy DeFreitas, David Heiman
Author-email: gdac@broadinstitute.org
License: UNKNOWN
Platform: UNKNOWN
